coollog/__init__.py
coollog/coollog.py
coollog-0.1.3.dist-info/METADATA
coollog-0.1.3.dist-info/WHEEL
coollog-0.1.3.dist-info/top_level.txt
coollog-0.1.3.dist-info/RECORD
