Metadata-Version: 2.4
Name: coollog
Version: 0.1.3
Summary: A simple and colorful logger for Python
Author-email: Mohammad Reza Hosein Nia <id.suzuya@email.com>
License: MIT
Project-URL: Homepage, https://github.com/mmd-dll/coollog
Project-URL: Bug Tracker, https://github.com/mmd-dll/coollog/issues
Keywords: logger,color,console,python
Classifier: Programming Language :: Python :: 3
Classifier: License :: OSI Approved :: MIT License
Classifier: Operating System :: OS Independent
